caretta/__init__.py
caretta/dynamic_time_warping.py
caretta/feature_extraction.py
caretta/helper.py
caretta/multiple_alignment.py
caretta/neighbor_joining.py
caretta/score_functions.py
caretta/superposition_functions.py
caretta/app/__init__.py
caretta/app/app_callbacks.py
caretta/app/app_helper.py
caretta/app/app_layout.py
caretta-0.1.2.data/scripts/caretta-app
caretta-0.1.2.data/scripts/caretta-cli
caretta-0.1.2.dist-info/LICENSE
caretta-0.1.2.dist-info/METADATA
caretta-0.1.2.dist-info/WHEEL
caretta-0.1.2.dist-info/entry_points.txt
caretta-0.1.2.dist-info/top_level.txt
caretta-0.1.2.dist-info/RECORD
