Metadata-Version: 2.1
Name: caretta
Version: 0.1.2
Summary: Fast multiple protein structure alignment
Home-page: https://github.com/TurtleTools/caretta
Author: Janani Durairaj, Mehmet Akdel
Author-email: janani.durairaj@gmail.com
License: MIT License
Project-URL: Source, https://github.com/TurtleTools/caretta
Project-URL: Tracker, https://github.com/TurtleTools/caretta/issues
Platform: UNKNOWN
Classifier: Intended Audience :: Science/Research
Classifier: Operating System :: Microsoft :: Windows
Classifier: Operating System :: POSIX
Classifier: Operating System :: Unix
Classifier: Operating System :: MacOS
Classifier: License :: OSI Approved :: MIT License
Classifier: Programming Language :: Python
Classifier: Programming Language :: Python :: 3
Classifier: Programming Language :: Python :: 3.7
Classifier: Programming Language :: Python :: 3.8
Classifier: Programming Language :: Python :: 3.9
Classifier: Topic :: Scientific/Engineering :: Bio-Informatics
Requires-Python: >=3.7
License-File: LICENSE
Requires-Dist: numpy
Requires-Dist: numba
Requires-Dist: scipy
Requires-Dist: prody
Requires-Dist: biopython
Requires-Dist: typer
Requires-Dist: pyparsing
Requires-Dist: geometricus
Requires-Dist: arviz
Provides-Extra: gui
Requires-Dist: dash (==1.3.1) ; extra == 'gui'
Requires-Dist: dash-bio (==0.1.4) ; extra == 'gui'
Requires-Dist: cryptography ; extra == 'gui'
Requires-Dist: dash-core-components (==1.2.1) ; extra == 'gui'
Requires-Dist: dash-html-components (==1.0.1) ; extra == 'gui'
Requires-Dist: dash-renderer (==1.1.0) ; extra == 'gui'
Requires-Dist: plotly (==3.7.1) ; extra == 'gui'
Requires-Dist: flask ; extra == 'gui'
